crpy/__init__.py
crpy/auth.py
crpy/cmd.py
crpy/common.py
crpy/image.py
crpy/registry.py
crpy/storage.py
crpy/version.py
crpy-0.2.0.dist-info/METADATA
crpy-0.2.0.dist-info/WHEEL
crpy-0.2.0.dist-info/entry_points.txt
crpy-0.2.0.dist-info/top_level.txt
crpy-0.2.0.dist-info/RECORD
