Metadata-Version: 2.4
Name: crpy
Version: 0.2.0
Summary: Simple and straight forward async library for interacting with container registry API.
Author-email: Brunno Vanelli <brunnovanelli@gmail.com>
Project-URL: Homepage, https://github.com/bvanelli/crpy
Project-URL: Repository, https://github.com/bvanelli/crpy.git
Project-URL: Bug Tracker, https://github.com/bvanelli/crpy/issues
Keywords: docker,oci,container-registry,api
Classifier: Programming Language :: Python
Classifier: Programming Language :: Python :: 3
Classifier: Programming Language :: Python :: 3.9
Classifier: Programming Language :: Python :: 3.10
Classifier: Programming Language :: Python :: 3.11
Classifier: Programming Language :: Python :: 3.12
Classifier: Programming Language :: Python :: 3.13
Requires-Python: >=3.9.0
Requires-Dist: requests>=2
Requires-Dist: async-lru>=2
Requires-Dist: aiohttp>=3
Requires-Dist: async-lru>=2
Requires-Dist: rich>=13.5
